{
  "manifest": {
    "publishingInformation": {
      "locales": {
        "en-GB": {
          "summary": "Test your knowledge of UK traffic signs.",
          "examplePhrases": [
            "Alexa, open Traffic Signs Quiz",
            "Alexa, launch Traffic Signs Quiz",
            "Alexa, start Traffic Signs Quiz"
          ],
          "keywords": [
            "quiz",
            "games",
            "road",
            "driving",
            "signs",
            "traffic signs",
            "road signs",
            "traffic"
          ],
          "name": "Traffic Signs Quiz",
          "description": "How well do you know your UK traffic signs? This skill will test you on a selection of official road traffic signals. You will need a device with a screen to play, or view the image cards on your Alexa companion app. \n\nTo start, just say \"Alexa, launch Traffic Signs Quiz\". At anytime, you can quit the game by saying \"Alexa, exit\""
        }
      },
      "isAvailableWorldwide": false,
      "testingInstructions": "No special testing tools needed.",
      "category": "KNOWLEDGE_AND_TRIVIA",
      "distributionCountries": []
    },
    "apis": {
      "custom": {
        "endpoint": {
          "sourceDir": "lambda/custom"
        }
      }
    },
    "manifestVersion": "1.0"
  }
}
